karrio/server/proxy/__init__.py
karrio/server/proxy/admin.py
karrio/server/proxy/apps.py
karrio/server/proxy/models.py
karrio/server/proxy/router.py
karrio/server/proxy/urls.py
karrio/server/proxy/migrations/__init__.py
karrio/server/proxy/tests/__init__.py
karrio/server/proxy/tests/test_pickup.py
karrio/server/proxy/tests/test_rating.py
karrio/server/proxy/tests/test_shipping.py
karrio/server/proxy/tests/test_tracking.py
karrio/server/proxy/views/__init__.py
karrio/server/proxy/views/manifest.py
karrio/server/proxy/views/pickup.py
karrio/server/proxy/views/rating.py
karrio/server/proxy/views/shipping.py
karrio/server/proxy/views/tracking.py
karrio_server_proxy-2026.1.4.dist-info/METADATA
karrio_server_proxy-2026.1.4.dist-info/WHEEL
karrio_server_proxy-2026.1.4.dist-info/top_level.txt
karrio_server_proxy-2026.1.4.dist-info/RECORD
